slack_cleaner/__init__.py
slack_cleaner/__main__.py
slack_cleaner/args.py
slack_cleaner/cli.py
slack_cleaner/utils.py
slack_cleaner-0.7.4.dist-info/LICENSE
slack_cleaner-0.7.4.dist-info/METADATA
slack_cleaner-0.7.4.dist-info/WHEEL
slack_cleaner-0.7.4.dist-info/entry_points.txt
slack_cleaner-0.7.4.dist-info/top_level.txt
slack_cleaner-0.7.4.dist-info/RECORD
