Metadata-Version: 2.1
Name: slack-cleaner
Version: 0.7.4
Summary: Bulk delete messages/files on Slack.
Home-page: https://github.com/sgratzl/slack-cleaner
Author: Lin, Ke-fei, Samuel Gratzl
Author-email: kfei@kfei.net, sam@sgratzl.com
License: MIT
Keywords: slack,clean,delete,message,file
Platform: UNKNOWN
Classifier: Development Status :: 5 - Production/Stable
Classifier: Intended Audience :: Developers
Classifier: License :: OSI Approved :: MIT License
Classifier: Operating System :: OS Independent
Classifier: Programming Language :: Python
Requires-Dist: setuptools
Requires-Dist: slacker (>=0.13)
Requires-Dist: colorama
